qwiic_ccs811.py
sparkfun_qwiic_ccs811-0.9.4.dist-info/LICENSE
sparkfun_qwiic_ccs811-0.9.4.dist-info/METADATA
sparkfun_qwiic_ccs811-0.9.4.dist-info/WHEEL
sparkfun_qwiic_ccs811-0.9.4.dist-info/top_level.txt
sparkfun_qwiic_ccs811-0.9.4.dist-info/RECORD
